pyvast/__init__.py
pyvast/test_vast.py
pyvast/vast.py
pyvast-2021.12.16.dist-info/METADATA
pyvast-2021.12.16.dist-info/WHEEL
pyvast-2021.12.16.dist-info/top_level.txt
pyvast-2021.12.16.dist-info/RECORD
