Metadata-Version: 2.1
Name: pyvast
Version: 2021.12.16
Summary: Python CLI wrapper for VAST - Visibility Across Space and Time
Home-page: https://github.com/tenzir/vast
Author: Tenzir
Author-email: engineering@tenzir.com
License: BSD 3-clause
Keywords: vast,pyvast,open source,network telemetry
Platform: UNKNOWN
Classifier: Development Status :: 3 - Alpha
Classifier: License :: OSI Approved :: BSD License
Classifier: Operating System :: MacOS :: MacOS X
Classifier: Operating System :: POSIX :: Linux
Classifier: Topic :: Scientific/Engineering :: Information Analysis
Classifier: Topic :: Scientific/Engineering :: Interface Engine/Protocol Translator
Classifier: Topic :: Security
Classifier: Topic :: Software Development :: Libraries :: Python Modules
Classifier: Topic :: System :: Software Distribution
Requires-Python: >=3.7
